axiom_math-3.0.0.dist-info/licenses/LICENSE
axiompy/__init__.py
axiompy/core.py
axiompy/v1_0.py
axiompy/v1_1.py
axiompy/v1_2.py
axiompy/v1_3.py
axiompy/v1_4.py
axiompy/v1_5.py
axiompy/v1_6.py
axiompy/v1_7.py
axiompy/v1_8.py
axiompy/v1_9.py
axiompy/v2_0.py
axiompy/v2_1.py
axiompy/v2_2.py
axiompy/v2_3.py
axiompy/v2_4.py
axiompy/v2_5.py
axiompy/v2_6.py
axiompy/v2_7.py
axiompy/v2_8.py
axiom_math-3.0.0.dist-info/METADATA
axiom_math-3.0.0.dist-info/WHEEL
axiom_math-3.0.0.dist-info/top_level.txt
axiom_math-3.0.0.dist-info/RECORD
